CMakeLists.txt
MANIFEST.in
README.md
pyproject.toml
setup.py
cmake/CMakeLists.txt
cmake/cln_config.py.in
cmake/config.py.in
cmake/core_config.py.in
cmake/parser_config.py.in
lib/pycarl/__init__.py
lib/pycarl/_config.py
lib/pycarl/_version.py
lib/pycarl/infinity.py
lib/pycarl.egg-info/PKG-INFO
lib/pycarl.egg-info/SOURCES.txt
lib/pycarl.egg-info/dependency_links.txt
lib/pycarl.egg-info/not-zip-safe
lib/pycarl.egg-info/requires.txt
lib/pycarl.egg-info/top_level.txt
lib/pycarl/cln/__init__.py
lib/pycarl/cln/_config.py
lib/pycarl/cln/formula/__init__.py
lib/pycarl/cln/formula/_config.py
lib/pycarl/cln/parse/__init__.py
lib/pycarl/cln/parse/_config.py
lib/pycarl/convert/__init__.py
lib/pycarl/convert/cln_converter.py
lib/pycarl/convert/gmp_converter.py
lib/pycarl/formula/__init__.py
lib/pycarl/gmp/__init__.py
lib/pycarl/gmp/formula/__init__.py
lib/pycarl/gmp/parse/__init__.py
lib/pycarl/gmp/parse/_config.py
lib/pycarl/parse/__init__.py
lib/pycarl/parse/_config.py
resources/include_pybind11.cmake
setup/__init__.py
setup/config.py
setup/helper.py
src/common.h
src/definitions.h.in
src/helpers.h
src/mod_cln.cpp
src/mod_core.cpp
src/mod_formula.cpp
src/mod_gmp.cpp
src/mod_parse.cpp
src/mod_typed_formula.cpp
src/mod_typed_parse.cpp
src/types.h
src/core/bound_type.cpp
src/core/bound_type.h
src/core/monomial.cpp
src/core/monomial.h
src/core/variable.cpp
src/core/variable.h
src/formula/formula_type.cpp
src/formula/formula_type.h
src/formula/relation.cpp
src/formula/relation.h
src/typed_core/factorization.cpp
src/typed_core/factorization.h
src/typed_core/factorizedpolynomial.cpp
src/typed_core/factorizedpolynomial.h
src/typed_core/factorizedrationalfunction.cpp
src/typed_core/factorizedrationalfunction.h
src/typed_core/integer.cpp
src/typed_core/integer.h
src/typed_core/interval.h
src/typed_core/polynomial.cpp
src/typed_core/polynomial.h
src/typed_core/rational.cpp
src/typed_core/rational.h
src/typed_core/rationalfunction.cpp
src/typed_core/rationalfunction.h
src/typed_core/term.cpp
src/typed_core/term.h
src/typed_formula/common.h
src/typed_formula/constraint.cpp
src/typed_formula/constraint.h
src/typed_formula/formula.cpp
src/typed_formula/formula.h
src/typed_formula/types.h
