Metadata-Version: 2.4
Name: pycarl
Version: 2.4.0
Summary: pycarl - Python Bindings for CArL
Home-page: https://github.com/moves-rwth/pycarl/
Author: S. Junges
Author-email: sebastian.junges@cs.rwth-aachen.de
Maintainer: M. Volk
Maintainer-email: matthias.volk@cs.rwth-aachen.de
Project-URL: Documentation, https://moves-rwth.github.io/pycarl/
Project-URL: Source, https://github.com/moves-rwth/pycarl/
Project-URL: Bug reports, https://github.com/moves-rwth/pycarl/issues
Classifier: Intended Audience :: Science/Research
Classifier: Topic :: Scientific/Engineering
Classifier: Topic :: Software Development :: Libraries :: Python Modules
Requires-Python: >=3.7
Provides-Extra: doc
Requires-Dist: Sphinx; extra == "doc"
Requires-Dist: sphinx-bootstrap-theme; extra == "doc"
Provides-Extra: dev
Requires-Dist: tox; extra == "dev"
Dynamic: author
Dynamic: author-email
Dynamic: classifier
Dynamic: description
Dynamic: description-content-type
Dynamic: home-page
Dynamic: maintainer
Dynamic: maintainer-email
Dynamic: project-url
Dynamic: provides-extra
Dynamic: requires-python
Dynamic: summary
